{
    "version": "1.4.1",
    "architecture": {
        "32bit": {
            "url": "https://github.com/ortfo/db/releases/download/v1.4.1/ortfodb_Windows_i386.zip",
            "bin": [
                "ortfodb_windows_386.exe"
            ],
            "hash": "ed93f83fc4eff89f9d1f0bb0ed6590e0873fa7c394980cdfb980c3a0adbf63ec"
        },
        "64bit": {
            "url": "https://github.com/ortfo/db/releases/download/v1.4.1/ortfodb_Windows_x86_64.zip",
            "bin": [
                "ortfodb_windows_amd64.exe"
            ],
            "hash": "da2d66aacd314ad41e9018eeeaf7f3e781f0b2dd471e1b5c7e6699c6d6716232"
        },
        "arm64": {
            "url": "https://github.com/ortfo/db/releases/download/v1.4.1/ortfodb_Windows_arm64.zip",
            "bin": [
                "ortfodb_windows_arm64.exe"
            ],
            "hash": "ff8871bf397d362d7fbbff005408590639c2cd5a3e428e069861d5939863a555"
        }
    },
    "homepage": "https://ortfo.org",
    "license": "MIT",
    "description": "A readable, easy and enjoyable way to manage portfolio databases using directories and text files.",
    "depends": [
        "imagemagick",
        "ffmpeg",
        "libwebp"
    ],
    "shortcuts": [
        [
            "ortfodb.exe",
            "ortfodb"
        ]
    ]
}